Workbook
Name Aporte: 'Simulador de Investimento'!$D$13
Name Patrimonio: 'Simulador de Investimento'!$D$16
Name Qtd_Anos: 'Simulador de Investimento'!$D$14
Name Rendimento_Carteira: 'Simulador de Investimento'!$D$9
Name Salario: 'Simulador de Investimento'!$D$8
Name Sugestao_Investimento: 'Simulador de Investimento'!$B$10
Name Taxa_mensal: 'Simulador de Investimento'!$D$15

Sheet Simulador de Investimento
B7: Configurações
B8: Salário | D8: 3000
B9: Rendimento Carteira | D9: 0.0089
B10: Sugestão de Investimento | D10: =D8*30% -> 900
B12: Investimento Mensal
B13: Quanto devo investir por mês? | D13: 900
B14: Por quantos anos devo investir? | D14: 5
B15: Qual é a Taxa de Rendimento mensal? | D15: 0.01079
B16: Quanto de patrimônio acumulado terei? | D16: =FV(Taxa_mensal,Qtd_Anos*12,Aporte*-1) -> 75399.223
B17: Quanto de dividendos mensais? | D17: =Patrimonio*Rendimento_Carteira -> 671.05308
B19: Cenários | D19: Dividendos
A20: 2 | B20: Quanto em 2 anos? | C20: =FV($D$15,$A20*12,$D$13*-1) -> 24504.865 | D20: =C20*Rendimento_Carteira -> 218.09329
A21: 5 | B21: Quanto em 5 anos? | C21: =FV($D$15,$A21*12,$D$13*-1) -> 75399.223 | D21: =C21*Rendimento_Carteira -> 671.05308
A22: 10 | B22: Quanto em 10 anos? | C22: =FV($D$15,$A22*12,$D$13*-1) -> 218955.79 | D22: =C22*Rendimento_Carteira -> 1948.7065
A23: 20 | B23: Quanto em 20 anos? | C23: =FV($D$15,$A23*12,$D$13*-1) -> 1012678.6 | D23: =C23*Rendimento_Carteira -> 9012.8392
A24: 30 | B24: Quantos em 30 anos? | C24: =FV($D$15,$A24*12,$D$13*-1) -> 3889952.7 | D24: =C24*Rendimento_Carteira -> 34620.579
B26: Perfil | D26: Agressivo
B27: Aporte mensal | D27: =Aporte -> 900
B29: Tipo de FII | C29: Percentual Sugerido | D29: Valores
B30: Papel | C30: =VLOOKUP($D$26&"-"&B30,'Tabela de Apoio'!$A:$D,4,FALSE) -> 0.5 | D30: =C30*$D$27 -> 450
B31: Tijolo | C31: =VLOOKUP($D$26&"-"&B31,'Tabela de Apoio'!$A:$D,4,FALSE) -> 0.1 | D31: =C31*$D$27 -> 90
B32: Híbridos | C32: =VLOOKUP($D$26&"-"&B32,'Tabela de Apoio'!$A:$D,4,FALSE) -> 0.05 | D32: =C32*$D$27 -> 45
B33: FOFs | C33: =VLOOKUP($D$26&"-"&B33,'Tabela de Apoio'!$A:$D,4,FALSE) -> 0.05 | D33: =C33*$D$27 -> 45
B34: Desenvolvimento | C34: =VLOOKUP($D$26&"-"&B34,'Tabela de Apoio'!$A:$D,4,FALSE) -> 0.2 | D34: =C34*$D$27 -> 180
B35: Hotelarias | C35: =VLOOKUP($D$26&"-"&B35,'Tabela de Apoio'!$A:$D,4,FALSE) -> 0.1 | D35: =C35*$D$27 -> 90
B36: Total | C36: =SUM(C30:C35) -> 1 | D36: =SUM(D30:D35) -> 900

Sheet Tabela de Apoio
A2: Chave Composta | B2: Perfil | C2: Tipo de FII | D2: Percentual
A3: =B3&"-"&C3 -> Conservador-Papel | B3: Conservador | C3: Papel | D3: 0.3 | H3: Percentual
A4: =B4&"-"&C4 -> Conservador-Tijolo | B4: Conservador | C4: Tijolo | D4: 0.5 | G4: Moderado-Tijolo | H4: =VLOOKUP(G4,$A:$D,4,) -> 0.35
A5: =B5&"-"&C5 -> Conservador-Híbridos | B5: Conservador | C5: Híbridos | D5: 0.1
A6: =B6&"-"&C6 -> Conservador-FOFs | B6: Conservador | C6: FOFs | D6: 0.1
A7: =B7&"-"&C7 -> Conservador-Desenvolvimento | B7: Conservador | C7: Desenvolvimento | D7: 0
A8: =B8&"-"&C8 -> Conservador-Hotelarias | B8: Conservador | C8: Hotelarias | D8: 0
A9: =B9&"-"&C9 -> Moderado-Papel | B9: Moderado | C9: Papel | D9: 0.32
A10: =B10&"-"&C10 -> Moderado-Tijolo | B10: Moderado | C10: Tijolo | D10: 0.35
A11: =B11&"-"&C11 -> Moderado-Híbridos | B11: Moderado | C11: Híbridos | D11: 0.08
A12: =B12&"-"&C12 -> Moderado-FOFs | B12: Moderado | C12: FOFs | D12: 0.05
A13: =B13&"-"&C13 -> Moderado-Desenvolvimento | B13: Moderado | C13: Desenvolvimento | D13: 0.1
A14: =B14&"-"&C14 -> Moderado-Hotelarias | B14: Moderado | C14: Hotelarias | D14: 0.1
A15: =B15&"-"&C15 -> Agressivo-Papel | B15: Agressivo | C15: Papel | D15: 0.5
A16: =B16&"-"&C16 -> Agressivo-Tijolo | B16: Agressivo | C16: Tijolo | D16: 0.1
... A20: =B20&"-"&C20 -> Agressivo-Hotelarias | B20: Agressivo | C20: Hotelarias | D20: 0.1
